{"cameraMode":{"drawMode":0,"name":"Shaded","section":"Shading Mode"},"sceneLighting":true,"audioPlay":false,"sceneViewState":{"m_AlwaysRefresh":false,"showFog":true,"showSkybox":true,"showFlares":true,"showImageEffects":true,"showParticleSystems":true,"showVisualEffectGraphs":true,"m_FxEnabled":true},"in2DMode":false,"pivot":{"x":604.48974609375,"y":0.27051401138305666,"z":761.1229248046875},"rotation":{"x":-0.05657424405217171,"y":0.914276659488678,"z":-0.13865870237350465,"w":-0.37671640515327456},"size":10.945822715759278,"orthographic":false}